[
	{
		"id": "1",
		"title": "first book",
		"imageUrl": "https://encrypted-tbn0.gstatic.com/images?q=tbn:ANd9GcRaL1EHwRJ3k_RMq90X6F96QCIdzHFsnVDAdg&usqp=CAU",
		"descriptions": " ipsum dolor, sit amet consectetur adipisicing elit. Eaque similique mollitia fuga id adipisci deserunt reiciendis assumenda, incidunt rem iure animi molestiae repudiandae ut soluta nesciunt placeat quas voluptate porro.",
		"price": "32"
	},
	{
		"id": "2",
		"title": "A demo book",
		"imageUrl": "https://encrypted-tbn0.gstatic.com/images?q=tbn:ANd9GcTq92ZPbEgGqCouW9J8EnEJGzDGuOQWiiJlOQ&usqp=CAU",
		"descriptions": "demo book",
		"price": "12"
	},
	{
		"id": "3",
		"title": "second book",
		"imageUrl": "https://encrypted-tbn0.gstatic.com/images?q=tbn:ANd9GcSf4tlciChngGIDXs47ll2ya00ltnBFznH2rA&usqp=CAU",
		"descriptions": "test",
		"price": "10"
	},
	{
		"id": "4",
		"title": "Harry poter",
		"imageUrl": "https://encrypted-tbn0.gstatic.com/images?q=tbn:ANd9GcRaL1EHwRJ3k_RMq90X6F96QCIdzHFsnVDAdg&usqp=CAU",
		"descriptions": "a book write by cedric karungu",
		"price": "29.26"
	}
]
